LICENSE
MANIFEST.in
README.rst
setup.py
remoto/__init__.py
remoto/bar.py
remoto/connection.py
remoto/exc.py
remoto/file_sync.py
remoto/log.py
remoto/process.py
remoto/util.py
remoto/zombie.py
remoto.egg-info/PKG-INFO
remoto.egg-info/SOURCES.txt
remoto.egg-info/dependency_links.txt
remoto.egg-info/not-zip-safe
remoto.egg-info/requires.txt
remoto.egg-info/top_level.txt
remoto/backends/__init__.py
remoto/backends/docker.py
remoto/backends/kubernetes.py
remoto/backends/local.py
remoto/backends/openshift.py
remoto/backends/podman.py
remoto/backends/ssh.py
remoto/tests/__init__.py
remoto/tests/conftest.py
remoto/tests/fake_module.py
remoto/tests/test_connection.py
remoto/tests/test_log.py
remoto/tests/test_process.py
remoto/tests/test_rsync.py
remoto/tests/test_util.py