Metadata-Version: 1.1
Name: remoto
Version: 1.1.5
Summary: Execute remote commands or processes.
Home-page: http://github.com/alfredodeza/remoto
Author: Alfredo Deza
Author-email: contact@deza.pe
License: MIT
Keywords: remote,commands,unix,ssh,socket,execute,terminal
Platform: UNKNOWN
Classifier: Development Status :: 4 - Beta
Classifier: Intended Audience :: Developers
Classifier: License :: OSI Approved :: MIT License
Classifier: Topic :: Utilities
Classifier: Operating System :: MacOS :: MacOS X
Classifier: Operating System :: POSIX
Classifier: Programming Language :: Python :: 2.6
Classifier: Programming Language :: Python :: 2.7
Classifier: Programming Language :: Python :: 3.3
